{
  "slug": "best-vpn-for-netherlands-2026",
  "title": "Best VPN for Netherlands 2026: Top Picks for Dutch Users",
  "description": "The best VPN for Netherlands in 2026: privacy laws, streaming access, and which providers work best for Dutch users.",
  "date": "2026-06-30",
  "category": "country-guides",
  "readTime": "6 min read",
  "content": "<article><p>The best VPN for the Netherlands in 2026 is NordVPN for most users, ExpressVPN for streaming, and Mullvad for maximum privacy. The Netherlands has strong data retention laws and requires ISPs to log user activity, which makes a VPN genuinely useful for Dutch residents who want to protect their browsing history.</p><h2>Why Dutch Users Need a VPN</h2><p>The Netherlands participates in the Nine Eyes intelligence sharing agreement, meaning your internet activity can be logged by your ISP and potentially shared with foreign governments. ISPs are legally required to retain connection data. A VPN encrypts your traffic before it reaches your ISP, preventing this logging at the source.</p><h2>Best VPN Providers for Netherlands (2026)</h2><h3>1. NordVPN (Best Overall)</h3><p>NordVPN has over 100 servers in the Netherlands (Amsterdam and Rotterdam) and strong no-log policy audited by PricewaterhouseCoopers. Dutch users connect to NL servers for local speed and to international servers for geo-restricted content. Price: from 3.99 euro per month on a 2-year plan.</p><h3>2. ExpressVPN (Best for Streaming)</h3><p>ExpressVPN reliably unblocks Netflix US, UK, and other regional catalogs from Dutch IP addresses. It also works with Videoland and NPO Start when traveling abroad. Slightly more expensive at 6.67 euro per month but the streaming reliability justifies the cost.</p><h3>3. Mullvad (Best for Privacy)</h3><p>Mullvad is a Swedish provider with no accounts: you pay anonymously with a randomly generated account number. Accepted payment methods include cash and cryptocurrency. No email required, no personal data collected. Price: 5 euro per month flat. Ideal for users who prioritize anonymity above all else.</p><h3>4. Surfshark (Best Budget)</h3><p>Surfshark offers unlimited simultaneous connections for 2.49 euro per month on a 2-year plan. Good for households or users with multiple devices. Netherlands servers available, slightly slower than NordVPN on peak hours.</p><h2>Is VPN Legal in the Netherlands?</h2><p>Yes, VPNs are completely legal in the Netherlands. Using a VPN for legitimate privacy protection, accessing geo-restricted content, or securing public Wi-Fi is legal. Using a VPN to commit crimes is illegal, but the VPN itself is not the issue.</p><h2>VPN for Dutch Streaming Services</h2><p>If you travel outside the Netherlands, a VPN with Dutch servers lets you access NPO Start, Videoland, and RTL XL as if you were home. Connect to a Netherlands server and these services see a Dutch IP address.</p><h2>Frequently Asked Questions</h2><h3>Do I need a VPN in the Netherlands?</h3><p>Not strictly required, but useful. ISPs are required to log connection data, and the Netherlands is in the Nine Eyes. A VPN prevents your ISP from seeing your browsing history and encrypts your traffic on public Wi-Fi networks.</p><h3>Which free VPN works in the Netherlands?</h3><p>Proton VPN Free has Dutch servers and no data limits, making it the best free option. Most free VPNs have data caps, slower speeds, or no Netherlands servers. Proton VPN Free is reliable but slower than paid plans.</p></article>"
}