{
  "slug": "best-vpn-for-privacy-2026",
  "title": "Best VPN for Privacy in 2026: No-Log Providers That Actually Deliver",
  "description": "Not all VPNs protect your privacy equally. Some log your activity despite claiming not to. Here are the providers with verified no-log policies and why it matters.",
  "date": "2026-06-09",
  "category": "reviews",
  "readTime": "5 min",
  "content": "<h2>Why No-Log Claims Are Not All Equal</h2><p>Every VPN provider claims to have a no-log policy. The difference is in what that means in practice and whether it has been independently verified. Some providers have had their claims tested by government requests or court orders, and the results were revealing. A true no-log provider has nothing to hand over when compelled by legal process.</p><h2>What a Real No-Log Policy Covers</h2><p>A meaningful no-log policy means no connection timestamps, no IP addresses, no DNS queries, no traffic content, and no session duration data. Some providers claim not to log traffic but do log connection times and original IPs. This is enough to identify which user was connected when, even without the traffic content.</p><h2>Mullvad VPN</h2><p>Mullvad requires no email address to create an account. You get an account number and pay anonymously. They have been audited multiple times and had their servers searched by Swedish police in 2023. The police left with nothing because there was nothing to find. For people who need privacy to be real rather than just marketed, Mullvad is the benchmark.</p><h2>ProtonVPN</h2><p>ProtonVPN is operated by the team behind ProtonMail, which has a long track record in privacy infrastructure. They are based in Switzerland with strong privacy laws. They have undergone independent audits. The free tier offers unlimited data, which is unusual. For users who want a trusted name with strong infrastructure, ProtonVPN is a consistent recommendation.</p><h2>IVPN</h2><p>IVPN is a smaller provider with a strong technical reputation. Like Mullvad, they do not require an email to sign up. They are audited regularly and publish the results. Their pricing is usage-based rather than bandwidth-based, which suits privacy-focused users who may not need a VPN continuously running.</p><h2>What to Avoid</h2><p>Free VPNs that make money from advertising or data sales, providers based in 14-Eyes countries with poor track records, and any provider that has had logs handed over to authorities despite no-log claims are worth avoiding if privacy is the goal.</p>"
}
