{
  "slug": "how-to-remove-yourself-from-the-internet",
  "title": "How to Remove Your Personal Data from the Internet in 2026",
  "description": "Data brokers sell your home address, phone number, and financial details to anyone who pays. Here is how to get your information removed, and why automated services beat manual requests.",
  "date": "2026-05-26",
  "category": "Privacy",
  "content": "## Who Has Your Personal Data Right Now?\n\nData brokers are companies that collect personal information from public records, social media, loyalty programs, and other sources, then sell that data to advertisers, marketers, background check services, and anyone else willing to pay.\n\nRight now, there are likely dozens of websites that list your full name, home address, phone number, estimated income, family member names, and past addresses. These sites are legal. Removing your data from them takes either significant time or money.\n\n## What Data Brokers Actually Sell\n\nThe most common data categories sold by brokers include:\n\n- **Contact information**: home address, phone number, email\n- **Personal history**: past addresses, relatives, neighbors\n- **Financial estimates**: income range, property value, credit score range\n- **Online activity**: browsing behavior, purchase history, device identifiers\n\nThis data gets used for targeted advertising, background checks, and unfortunately, doxxing. If someone wants to find your home address, data broker sites make it trivial.\n\n## Why Manual Removal Does Not Scale\n\nYou can contact each data broker directly and request removal. Most are legally required to comply under CCPA (California), GDPR (EU), and similar laws. The problem: there are 750+ active data broker sites. Each has a different removal process. Many require ID verification. And most re-add your data within months from new public record updates.\n\nDoing this manually takes 50-100+ hours. Then you have to repeat it every six months.\n\n## The Two Best Automated Removal Services\n\n### DeleteMe: Best for US Users\n\n**DeleteMe** sends removal requests to 750+ data brokers using a team of human reviewers, not just bots. Human verification matters because many brokers require you to confirm removals through email links or secondary steps. Automated tools miss these steps, so data reappears quickly.\n\nDeleteMe provides detailed PDF reports showing exactly which sites had your data and what was removed. Annual re-scans catch reappearing data. Family member add-ons extend coverage to your household.\n\nPricing: $10.75/mo (billed annually). Coverage is primarily US-focused.\n\n[Read our full DeleteMe review](/tools/deleteme)\n\n### Incogni: Best for EU Users and Budget Users\n\n**Incogni**, built by the Surfshark team, uses GDPR and CCPA legal frameworks to send removal requests. Brokers are legally required to respond to these requests, which gives Incogni real leverage that informal automated requests lack.\n\nIncogni covers 180+ brokers, fewer than DeleteMe's 750+, but its GDPR coverage makes it particularly effective for users in Europe where data broker operations are tightly regulated. At $6.49/mo, it costs roughly half what DeleteMe charges.\n\n[Read our full Incogni review](/tools/incogni)\n\n## DeleteMe vs Incogni: Quick Comparison\n\n| | DeleteMe | Incogni |\n|---|---|---|\n| Brokers covered | 750+ | 180+ |\n| Price/mo | $10.75 | $6.49 |\n| Geographic focus | US | US + EU |\n| Removal method | Human-verified | Automated (GDPR/CCPA) |\n| Reporting | Detailed PDF reports | Dashboard |\n| Family add-ons | Yes | No |\n\n## Other Steps Worth Taking\n\nData removal services handle broker sites, but they do not cover everything. These steps complement them:\n\n1. **Google yourself** and request removal of any search results showing your address via Google's Results About You tool.\n2. **Delete old social media accounts** you no longer use. Inactive profiles are data collection points.\n3. **Use a VPN** to stop your ISP from logging your browsing activity and selling it.\n4. **Opt out of data sharing** in apps you use. Most have settings buried in privacy menus.\n\n## The Verdict\n\nIf you are in the US and want comprehensive coverage, use **DeleteMe**. The human verification step and 750+ broker coverage justify the higher price.\n\nIf you are in the EU, on a budget, or want a fully hands-off automated process, use **Incogni**. The legal framework it uses gives it real power with EU brokers specifically."
}
